pydiameter2json/__init__.py
pydiameter2json/__main__.py
pydiameter2json/main.py
pydiameter2json-0.1.0.dist-info/METADATA
pydiameter2json-0.1.0.dist-info/WHEEL
pydiameter2json-0.1.0.dist-info/top_level.txt
pydiameter2json-0.1.0.dist-info/RECORD
