Metadata-Version: 2.4
Name: pydiameter2json
Version: 0.1.0
Summary: A Python library to convert Diameter protocol messages to JSON.
License: MIT
Classifier: Development Status :: 3 - Alpha
Classifier: Intended Audience :: Developers
Classifier: License :: OSI Approved :: MIT License
Classifier: Programming Language :: Python :: 3
Classifier: Programming Language :: Python :: 3.12
Classifier: Topic :: Software Development :: Libraries :: Python Modules
Requires-Python: >=3.12
Requires-Dist: diameter-codec>=1.0.3
Requires-Dist: python-diameter>=0.7.4
Requires-Dist: typer>=0.15.2
